numeral_system/__init__.py
numeral_system/exceptions.py
numeral_system/positional.py
numeral_system/roman.py
numeral_system_py-0.2.0.dist-info/LICENSE
numeral_system_py-0.2.0.dist-info/METADATA
numeral_system_py-0.2.0.dist-info/WHEEL
numeral_system_py-0.2.0.dist-info/top_level.txt
numeral_system_py-0.2.0.dist-info/RECORD
