Metadata-Version: 2.1
Name: numeral-system-py
Version: 0.2.0
Summary: Package which contains function for converting between different number system
Home-page: https://github.com/zifter/numeral-system-py
Author: Oleg Strokachuk
Author-email: zifter.ai@gmail.com
License: MIT
Keywords: roman,positional,ui,number,numeral,system
Platform: any
Classifier: Development Status :: 4 - Beta
Classifier: Intended Audience :: Developers
Classifier: License :: OSI Approved :: MIT License
Classifier: Programming Language :: Python
Classifier: Programming Language :: Python :: 2.7
Classifier: Programming Language :: Python :: 3.5
Classifier: Programming Language :: Python :: 3.6
Classifier: Programming Language :: Python :: 3.7
Classifier: Programming Language :: Python :: 3.8
Classifier: Topic :: Software Development :: User Interfaces
Classifier: Operating System :: OS Independent
Classifier: Topic :: Text Processing
Requires-Python: >= 2.7
Requires-Dist: backports.functools-lru-cache
